{
  "version": "0.0.1",
  "records": [
    {
      "id": 100101,
      "group_id": 1001,
      "description_type": "None",
      "description_localkey": "Locale_System:SHOP_INFO_NORMAL_DESC"
    },
    {
      "id": 100102,
      "group_id": 1001,
      "description_type": "None",
      "description_localkey": "Locale_System:SHOP_INFO_ITEM_RECOMMEND_DESC"
    },
    {
      "id": 100103,
      "group_id": 1001,
      "description_type": "None",
      "description_localkey": "Locale_System:SHOP_INFO_RESTORE_DESC"
    },
    {
      "id": 100104,
      "group_id": 1001,
      "description_type": "None",
      "description_localkey": "Locale_System:SHOP_INFO_MANUAL_DESC"
    },
    {
      "id": 700101,
      "group_id": 7001,
      "description_type": "None",
      "description_localkey": "Locale_System:SHOP_INFO_GUILD_DESC"
    },
    {
      "id": 700102,
      "group_id": 7001,
      "description_type": "None",
      "description_localkey": "Locale_System:SHOP_INFO_ITEM_RECOMMEND_DESC"
    },
    {
      "id": 700103,
      "group_id": 7001,
      "description_type": "None",
      "description_localkey": "Locale_System:SHOP_INFO_RESTORE_DESC"
    },
    {
      "id": 1200101,
      "group_id": 12001,
      "description_type": "None",
      "description_localkey": "Locale_System:SHOP_INFO_PIECE_DESC"
    },
    {
      "id": 1200102,
      "group_id": 12001,
      "description_type": "None",
      "description_localkey": "Locale_System:SHOP_INFO_RESTORE_DESC"
    },
    {
      "id": 1300101,
      "group_id": 13001,
      "description_type": "None",
      "description_localkey": "Locale_System:SHOP_INFO_ARENA_DESC"
    },
    {
      "id": 1300102,
      "group_id": 13001,
      "description_type": "None",
      "description_localkey": "Locale_System:SHOP_INFO_ITEM_RECOMMEND_DESC"
    },
    {
      "id": 1300103,
      "group_id": 13001,
      "description_type": "None",
      "description_localkey": "Locale_System:SHOP_INFO_RESTORE_DESC"
    },
    {
      "id": 1400101,
      "group_id": 14001,
      "description_type": "None",
      "description_localkey": "Locale_System:SHOP_INFO_COOPERATION_DESC"
    },
    {
      "id": 1400102,
      "group_id": 14001,
      "description_type": "None",
      "description_localkey": "Locale_System:SHOP_INFO_RESTORE_DESC"
    },
    {
      "id": 1700101,
      "group_id": 17001,
      "description_type": "None",
      "description_localkey": "Locale_System:SHOP_INFO_MILEAGE_DESC"
    },
    {
      "id": 1700102,
      "group_id": 17001,
      "description_type": "None",
      "description_localkey": "Locale_System:SHOP_INFO_RESTORE_DESC"
    }
  ]
}