{
  "version": "0.0.1",
  "records": [
    {
      "id": 1001,
      "name": "Locale_DaveSystem:YX001_ROLE/ANCHOR",
      "desc": "NIKKE ANCHOR",
      "icon": "DD_Icon_Anko1",
      "asset": "DD_Spine_Anko"
    },
    {
      "id": 1002,
      "name": "Locale_DaveSystem:YX001_ROLE/MAST",
      "desc": "NIKKE MAST",
      "icon": "DD_Icon_Master1",
      "asset": "DD_Spine_Master"
    },
    {
      "id": 1003,
      "name": "Locale_DaveSystem:YX001_ROLE/HELM",
      "desc": "NIKKE HELM",
      "icon": "DD_Icon_Halen1",
      "asset": "DD_Spine_Halen"
    },
    {
      "id": 1004,
      "name": "Locale_DaveSystem:YX001_ROLE/BANCHO",
      "desc": "DD BANCHO",
      "icon": "DD_Icon_Bancho1",
      "asset": "DD_Spine_Bancho"
    },
    {
      "id": 1005,
      "name": "Locale_DaveSystem:YX001_ROLE/DAVE",
      "desc": "DD DAVE_restaurant",
      "icon": "DD_Icon_Dave1",
      "asset": "DD_Spine_Dave"
    },
    {
      "id": 1006,
      "name": "Locale_DaveSystem:YX001_ROLE/MAKI",
      "desc": "DD MAKI",
      "icon": "DD_Icon_Cooker1",
      "asset": "DD_Spine_Cooker1"
    },
    {
      "id": 1007,
      "name": "Locale_DaveSystem:YX001_ROLE/KYOKO",
      "desc": "DD KYOKO",
      "icon": "DD_Icon_Waiter1",
      "asset": "DD_Spine_Waiter1"
    },
    {
      "id": 1008,
      "name": "Locale_DaveSystem:YX001_ROLE/DAVE",
      "desc": "Desc Customer1",
      "icon": "DD_Icon_Customer1",
      "asset": "DD_Spine_Customer1"
    },
    {
      "id": 1009,
      "name": "Locale_DaveSystem:YX001_ROLE/DAVE",
      "desc": "Desc Customer2",
      "icon": "DD_Icon_Customer2",
      "asset": "DD_Spine_Customer2"
    },
    {
      "id": 1010,
      "name": "Locale_DaveSystem:YX001_ROLE/DAVE",
      "desc": "Desc Customer3",
      "icon": "DD_Icon_Customer3",
      "asset": "DD_Spine_Customer3"
    },
    {
      "id": 1011,
      "name": "Locale_DaveSystem:YX001_ROLE/DAVE",
      "desc": "Desc Customer4",
      "icon": "DD_Icon_Customer4",
      "asset": "DD_Spine_Customer4"
    },
    {
      "id": 1012,
      "name": "Locale_DaveSystem:YX001_ROLE/DAVE",
      "desc": "Desc Customer5",
      "icon": "DD_Icon_Customer5",
      "asset": "DD_Spine_Customer5"
    },
    {
      "id": 1013,
      "name": "Locale_DaveSystem:YX001_ROLE/DAVE",
      "desc": "Desc Customer6",
      "icon": "DD_Icon_Customer6",
      "asset": "DD_Spine_Customer6"
    },
    {
      "id": 1014,
      "name": "Locale_DaveSystem:YX001_ROLE/DAVE",
      "desc": "Desc Customer7",
      "icon": "DD_Icon_Customer7",
      "asset": "DD_Spine_Customer7"
    },
    {
      "id": 1015,
      "name": "Locale_DaveSystem:YX001_ROLE/BANCHO",
      "desc": "DD Bancho_knife",
      "icon": "DD_Icon_Bancho2",
      "asset": "DD_Spine_Bancho"
    },
    {
      "id": 1016,
      "name": "Locale_DaveSystem:YX001_ROLE/DAVE",
      "desc": "DD Dave_sushicj",
      "icon": "DD_Icon_Dave2",
      "asset": "DD_Spine_Dave"
    },
    {
      "id": 1017,
      "name": "Locale_DaveSystem:YX001_ROLE/DAVE",
      "desc": "DD Dave_board",
      "icon": "DD_Icon_Dave3",
      "asset": "DD_Spine_Dave"
    },
    {
      "id": 1018,
      "name": "Locale_DaveSystem:YX001_ROLE/DAVE",
      "desc": "DD Dave_boardcj",
      "icon": "DD_Icon_Dave4",
      "asset": "DD_Spine_Dave"
    }
  ]
}