{
  "version": "0.0.1",
  "records": [
    {
      "id": 30101,
      "group": 301,
      "repeat_type": "Next",
      "battle_count_condition": 5,
      "hint_time_value": 1500,
      "battle_time_value": 0,
      "burst_time_value": 0
    },
    {
      "id": 30102,
      "group": 301,
      "repeat_type": "Next",
      "battle_count_condition": 5,
      "hint_time_value": 1000,
      "battle_time_value": 0,
      "burst_time_value": 0
    },
    {
      "id": 30103,
      "group": 301,
      "repeat_type": "Next",
      "battle_count_condition": 10,
      "hint_time_value": 800,
      "battle_time_value": 0,
      "burst_time_value": 0
    },
    {
      "id": 30104,
      "group": 301,
      "repeat_type": "Next",
      "battle_count_condition": 10,
      "hint_time_value": 800,
      "battle_time_value": 0,
      "burst_time_value": 0
    },
    {
      "id": 30105,
      "group": 301,
      "repeat_type": "Repeat",
      "battle_count_condition": 10,
      "hint_time_value": 0,
      "battle_time_value": 0,
      "burst_time_value": 0
    },
    {
      "id": 40101,
      "group": 401,
      "repeat_type": "Next",
      "battle_count_condition": 20,
      "hint_time_value": 800,
      "battle_time_value": 0,
      "burst_time_value": 0
    },
    {
      "id": 40102,
      "group": 401,
      "repeat_type": "Next",
      "battle_count_condition": 20,
      "hint_time_value": 800,
      "battle_time_value": 0,
      "burst_time_value": 0
    },
    {
      "id": 40103,
      "group": 401,
      "repeat_type": "Next",
      "battle_count_condition": 20,
      "hint_time_value": 600,
      "battle_time_value": 0,
      "burst_time_value": 0
    },
    {
      "id": 40104,
      "group": 401,
      "repeat_type": "Next",
      "battle_count_condition": 20,
      "hint_time_value": 600,
      "battle_time_value": 0,
      "burst_time_value": 0
    },
    {
      "id": 40105,
      "group": 401,
      "repeat_type": "Next",
      "battle_count_condition": 20,
      "hint_time_value": 500,
      "battle_time_value": 0,
      "burst_time_value": 0
    },
    {
      "id": 40106,
      "group": 401,
      "repeat_type": "Next",
      "battle_count_condition": 10,
      "hint_time_value": 300,
      "battle_time_value": 0,
      "burst_time_value": 0
    },
    {
      "id": 40107,
      "group": 401,
      "repeat_type": "Repeat",
      "battle_count_condition": 10,
      "hint_time_value": 100,
      "battle_time_value": 0,
      "burst_time_value": 0
    }
  ]
}